activewindow/__init__.py
activewindow/classes.py
activewindow/winInfo.py
activewindow-0.4.4.dist-info/METADATA
activewindow-0.4.4.dist-info/WHEEL
activewindow-0.4.4.dist-info/top_level.txt
activewindow-0.4.4.dist-info/RECORD
